marmoolak/__init__.py
marmoolak-1.0.8.dist-info/DESCRIPTION.rst
marmoolak-1.0.8.dist-info/METADATA
marmoolak-1.0.8.dist-info/RECORD
marmoolak-1.0.8.dist-info/WHEEL
marmoolak-1.0.8.dist-info/metadata.json
marmoolak-1.0.8.dist-info/top_level.txt
