Metadata-Version: 2.0
Name: marmoolak
Version: 1.0.8
Summary: Yet another finite state machine with memory and callbacks.
Home-page: https://github.com/ourway/marmoolak
Author: Farsheed Ashouri
Author-email: rodmena@me.com
License: Apache 2.0
Keywords: fsm workflow engine disk memory easy simple iran tehran
Platform: UNKNOWN
Classifier: Development Status :: 5 - Production/Stable
Classifier: Environment :: Web Environment
Classifier: Natural Language :: English
Classifier: Intended Audience :: Developers
Classifier: License :: OSI Approved :: Apache Software License
Classifier: Operating System :: MacOS :: MacOS X
Classifier: Operating System :: Microsoft :: Windows
Classifier: Operating System :: POSIX
Classifier: Topic :: Software Development :: Libraries :: Python Modules
Classifier: Programming Language :: Python
Classifier: Programming Language :: Python :: Implementation :: CPython
Classifier: Programming Language :: Python :: Implementation :: PyPy
Classifier: Programming Language :: Python :: Implementation :: Jython
Classifier: Programming Language :: Python :: 2.7
Classifier: Programming Language :: Python :: 3.5
Requires-Dist: fysom
Requires-Dist: redis
